{
  "schemaVersion": "1.0.0",
  "sources": [
    {
      "sourceId": "moe-gf0025-2021-standard",
      "title": "国际中文教育中文水平等级标准 GF0025-2021",
      "publisher": "Ministry of Education of the People's Republic of China and State Language Commission",
      "sourceType": "official-standard",
      "url": "https://www.moe.gov.cn/jyb_sjzl/ziliao/A19/202111/t20211118_580755.html",
      "accessDate": "2026-07-23",
      "syllabusVersion": "GF0025-2021",
      "levels": [1,2,3,4,5,6,7,8,9],
      "scope": ["proficiency-levels","communication","topics","hanzi","vocabulary","grammar","listening","speaking","reading","writing","translation"],
      "confidence": "authoritative",
      "licenseStatus": "reuse-limited",
      "licenseNote": "Used for alignment and short attribution only; do not republish the full standard or protected appendices without permission review.",
      "derivedDataNote": "Production records must preserve this source ID and contain newly authored examples and exercises."
    },
    {
      "sourceId": "moe-gf0025-2021-qa",
      "title": "Official Q&A on the Chinese Proficiency Grading Standards",
      "publisher": "Ministry of Education of the People's Republic of China",
      "sourceType": "official-explanation",
      "url": "https://www.moe.gov.cn/jyb_xwfb/s271/202104/t20210402_524194.html",
      "accessDate": "2026-07-23",
      "syllabusVersion": "GF0025-2021",
      "levels": [1,2,3,4,5,6,7,8,9],
      "scope": ["version-history","quantitative-totals","implementation-scope","skill-framework"],
      "confidence": "authoritative",
      "licenseStatus": "reuse-limited",
      "licenseNote": "May be cited briefly; not a substitute for level-by-level source extraction.",
      "derivedDataNote": "Use to verify framework totals and scope only."
    },
    {
      "sourceId": "cti-hsk3-current-syllabus-2026",
      "title": "HSK 3.0 Examination Syllabus, Sample Questions and Competency Profile",
      "publisher": "Chinese Testing International / Chinese Test Service",
      "sourceType": "official-exam-syllabus",
      "url": "https://www.chinesetest.cn/syllabus",
      "accessDate": "2026-07-23",
      "syllabusVersion": "CTI-HSK3.0-2026",
      "levels": [1,2,3,4,5,6,"7-9"],
      "scope": ["tasks","topics","vocabulary","hanzi","grammar","sample-blueprints","competency-profile"],
      "confidence": "authoritative-current",
      "licenseStatus": "reuse-limited",
      "licenseNote": "Use public blueprint and competency requirements only; do not copy full sample tests, answer keys or audio.",
      "derivedDataNote": "All VDuckie exercises, transcripts and distractors must be newly authored."
    },
    {
      "sourceId": "cti-hsk79-first-test-2022",
      "title": "Official announcement of the first global HSK 7-9 examination",
      "publisher": "Chinese Testing International",
      "sourceType": "official-announcement",
      "url": "https://admin.chinesetest.cn/gonewcontent.do?id=46783143",
      "accessDate": "2026-07-23",
      "syllabusVersion": "CTI-HSK7-9",
      "levels": ["7-9"],
      "scope": ["exam-status","combined-advanced-exam"],
      "confidence": "authoritative",
      "licenseStatus": "reuse-limited",
      "licenseNote": "Status verification only; not a content source.",
      "derivedDataNote": "Do not use to assign separate official vocabulary bands for levels 7, 8 and 9."
    },
    {
      "sourceId": "cti-test-calendar-2026",
      "title": "2026 Chinese Test Calendar",
      "publisher": "Chinese Testing International / Chinese Test Service",
      "sourceType": "official-current-status",
      "url": "https://admin.chinesetest.cn/gonewcontent.do?id=48998697",
      "accessDate": "2026-07-23",
      "syllabusVersion": "CTI-Calendar-2026",
      "levels": [1,2,3,4,5,6,"7-9"],
      "scope": ["current-exam-implementation","calendar"],
      "confidence": "authoritative-current",
      "licenseStatus": "reuse-limited",
      "licenseNote": "Current-status reference; re-check before major release.",
      "derivedDataNote": "No learning content is derived from the calendar."
    },
    {
      "sourceId": "cc-cedict-current",
      "title": "CC-CEDICT",
      "publisher": "CC-CEDICT editor community / MDBG",
      "sourceType": "supplemental-dictionary",
      "url": "https://cc-cedict.org/wiki/",
      "accessDate": "2026-07-23",
      "syllabusVersion": "cross-level",
      "levels": ["cross-level"],
      "scope": ["pinyin-cross-check","gloss-cross-check","part-of-speech-cross-check"],
      "confidence": "supplemental",
      "licenseStatus": "verified",
      "licenseNote": "CC BY-SA 3.0; derivative redistribution must preserve attribution and ShareAlike obligations.",
      "derivedDataNote": "May not determine HSK level by itself."
    },
    {
      "sourceId": "unicode-unihan-17",
      "title": "Unicode Standard Annex #38: Unicode Han Database",
      "publisher": "Unicode Consortium",
      "sourceType": "supplemental-character-data",
      "url": "https://www.unicode.org/reports/tr38/",
      "accessDate": "2026-07-23",
      "syllabusVersion": "Unicode-17",
      "levels": ["cross-level"],
      "scope": ["character-codepoint","radical-stroke-index","variant-cross-check"],
      "confidence": "authoritative-technical",
      "licenseStatus": "verified",
      "licenseNote": "Use under Unicode Terms of Use.",
      "derivedDataNote": "Not a stroke-order animation source and not an HSK-level source."
    },
    {
      "sourceId": "legacy-ivankra-hsk30",
      "title": "ivankra/hsk30 cleaned HSK 3.0 vocabulary",
      "publisher": "ivankra",
      "sourceType": "legacy-derived-dataset",
      "url": "https://github.com/ivankra/hsk30",
      "accessDate": "2026-07-23",
      "syllabusVersion": "derived-HSK3.0",
      "levels": [1,2,3,4,5,6,"7-9"],
      "scope": ["legacy-v79-vocabulary","pinyin","part-of-speech","variants"],
      "confidence": "supplemental-needs-verification",
      "licenseStatus": "review-required",
      "licenseNote": "Repository declares MIT, but underlying official and third-party data provenance and redistribution rights require legal review.",
      "derivedDataNote": "Blocked from automatically making a level production-ready."
    },
    {
      "sourceId": "legacy-cvdict",
      "title": "CVDICT Chinese-Vietnamese dictionary",
      "publisher": "Phong Phan",
      "sourceType": "legacy-derived-dataset",
      "url": "https://github.com/ph0ngp/CVDICT",
      "accessDate": "2026-07-23",
      "syllabusVersion": "cross-level",
      "levels": ["cross-level"],
      "scope": ["legacy-v79-vietnamese-gloss"],
      "confidence": "supplemental-needs-human-review",
      "licenseStatus": "review-required",
      "licenseNote": "CC BY-SA 4.0; project notes indicate many translations were machine-assisted and may contain errors.",
      "derivedDataNote": "Vietnamese text must be human-reviewed before production-ready status."
    }
  ]
}
